{
  "allNotionPage": {
    "nodes": [
      {
        "id": "5cd00a50-29c7-5047-9bff-c6e0ffcbb887",
        "properties": {
          "Tags": { "multi_select": [{ "name": "Design" }, { "name": "UX" }] },
          "Thumbnail": { "url": "https://via.placeholder.com/250" },
          "Short_Desc": { "rich_text": [{ "plain_text": "a short desc " }] },
          "Body": {
            "rich_text": [
              {
                "plain_text": "Lorem ipsum dolor sit amet, consectetur adipiscing elit, sed do eiusmod tempor incididunt ut labore et dolore magna aliqua. Lorem mollis aliquam ut porttitor leo a diam sollicitudin. Ultricies lacus sed turpis tincidunt id aliquet. Sit amet consectetur adipiscing elit. Volutpat est velit egestas dui. Amet massa vitae tortor condimentum lacinia quis vel. Sodales neque sodales ut etiam sit. Venenatis cras sed felis eget velit aliquet sagittis id consectetur. Semper quis lectus nulla at volutpat diam ut. Nulla posuere sollicitudin aliquam ultrices sagittis orci a scelerisque purus. Senectus et netus et malesuada.\n\nNon sodales neque sodales ut etiam sit amet. Adipiscing enim eu turpis egestas pretium aenean pharetra magna ac. Est placerat in egestas erat imperdiet sed euismod. Ullamcorper dignissim cras tincidunt lobortis feugiat. Platea dictumst quisque sagittis purus sit amet volutpat consequat. Sagittis id consectetur purus ut faucibus. Non pulvinar neque laoreet suspendisse interdum. Mattis nunc sed blandit libero. In metus vulputate eu scelerisque felis imperdiet proin. Orci dapibus ultrices in iaculis. Est ante in nibh mauris cursus mattis molestie. Nulla porttitor massa id neque aliquam vestibulum morbi. Tincidunt dui ut ornare lectus. Cras semper auctor neque vitae tempus quam pellentesque nec. Adipiscing at in tellus integer. Dignissim cras tincidunt lobortis feugiat vivamus.\n\nSenectus et netus et malesuada fames ac turpis. Ac turpis egestas maecenas pharetra convallis posuere morbi leo. Augue lacus viverra vitae congue eu consequat. Sed pulvinar proin gravida hendrerit lectus a. Tellus molestie nunc non blandit massa enim nec dui. Fermentum odio eu feugiat pretium nibh ipsum consequat nisl. Malesuada fames ac turpis egestas sed tempus urna. A condimentum vitae sapien pellentesque habitant morbi tristique. Interdum varius sit amet mattis vulputate enim nulla aliquet porttitor. Scelerisque viverra mauris in aliquam sem fringilla ut. Ornare arcu odio ut sem nulla. Lorem ipsum dolor sit amet consectetur adipiscing elit pellentesque. Erat velit scelerisque in dictum non consectetur a. Volutpat maecenas volutpat blandit aliquam etiam erat velit scelerisque in."
              }
            ]
          },
          "Name": { "title": [{ "plain_text": "Peaches App Redesign" }] }
        }
      },
      {
        "id": "b01449c3-dcba-5bdc-b11a-77773607a631",
        "properties": {
          "Tags": { "multi_select": [{ "name": "Design" }, { "name": "UX" }] },
          "Thumbnail": {
            "url": "https://via.placeholder.com/250https://i.imgur.com/wSlxzC3.jpg"
          },
          "Short_Desc": { "rich_text": [{ "plain_text": "a short desc " }] },
          "Body": {
            "rich_text": [{ "plain_text": "Here is some description of flare" }]
          },
          "Name": { "title": [{ "plain_text": "Flare" }] }
        }
      },
      {
        "id": "08b08099-ab17-5d72-af82-eb6ac5726733",
        "properties": {
          "Tags": { "multi_select": [{ "name": "Design" }] },
          "Thumbnail": { "url": "https://via.placeholder.com/250" },
          "Short_Desc": { "rich_text": [{ "plain_text": "a short desc " }] },
          "Body": { "rich_text": [{ "plain_text": "red bubble description" }] },
          "Name": { "title": [{ "plain_text": "Red Bubble" }] }
        }
      }
    ]
  }
}
